{"contract_id":"04_02_111_CHR14","target_local_start_timestamp":"2022-12-01T00:00:00.000Z","target_local_end_timestamp":"2023-03-03T00:00:00.000Z","tariff_name":"Digital Electric","charge_type":"buy","price":0.3182}
{"contract_id":"04_02_111_CHR14","target_local_start_timestamp":"2023-03-03T00:00:00.000Z","target_local_end_timestamp":"2024-07-01T00:00:00.000Z","tariff_name":"Electric Pro","charge_type":"buy","price":0.2086}
{"contract_id":"04_02_111_CHR14","target_local_start_timestamp":"2024-07-01T00:00:00.000Z","target_local_end_timestamp":"2024-10-20T00:00:00.000Z","tariff_name":"Business Electric","charge_type":"buy","price":0.4377}
{"contract_id":"04_02_111_CHR14","target_local_start_timestamp":"2024-10-20T00:00:00.000Z","target_local_end_timestamp":"2024-11-30T00:00:00.000Z","tariff_name":"Electric Optim","charge_type":"buy","price":0.2357}
{"contract_id":"04_02_111_CHR14","target_local_start_timestamp":"2024-11-30T00:00:00.000Z","target_local_end_timestamp":"2025-01-01T00:00:00.000Z","tariff_name":"Digital Electric","charge_type":"buy","price":0.1729}
{"contract_id":"04_02_111_CHR14","target_local_start_timestamp":"2022-12-01T00:00:00.000Z","target_local_end_timestamp":"2023-03-03T00:00:00.000Z","tariff_name":"SState","charge_type":"sell","price":0.1277}
{"contract_id":"04_02_111_CHR14","target_local_start_timestamp":"2023-03-03T00:00:00.000Z","target_local_end_timestamp":"2024-07-01T00:00:00.000Z","tariff_name":"SState","charge_type":"sell","price":0.0838}
{"contract_id":"04_02_111_CHR14","target_local_start_timestamp":"2024-07-01T00:00:00.000Z","target_local_end_timestamp":"2024-10-20T00:00:00.000Z","tariff_name":"EctoGrid","charge_type":"sell","price":0.0947}
{"contract_id":"04_02_111_CHR14","target_local_start_timestamp":"2024-10-20T00:00:00.000Z","target_local_end_timestamp":"2024-11-30T00:00:00.000Z","tariff_name":"OpCom","charge_type":"sell","price":0.0696}
{"contract_id":"04_02_111_CHR14","target_local_start_timestamp":"2024-11-30T00:00:00.000Z","target_local_end_timestamp":"2025-01-01T00:00:00.000Z","tariff_name":"EctoGrid","charge_type":"sell","price":0.1212}
{"contract_id":"10_01_147_CHR","target_local_start_timestamp":"2022-12-01T00:00:00.000Z","target_local_end_timestamp":"2023-03-03T00:00:00.000Z","tariff_name":"Electric Pro","charge_type":"buy","price":0.1924}
{"contract_id":"10_01_147_CHR","target_local_start_timestamp":"2023-03-03T00:00:00.000Z","target_local_end_timestamp":"2024-07-01T00:00:00.000Z","tariff_name":"Electric Optim","charge_type":"buy","price":0.2117}
{"contract_id":"10_01_147_CHR","target_local_start_timestamp":"2024-07-01T00:00:00.000Z","target_local_end_timestamp":"2024-10-20T00:00:00.000Z","tariff_name":"Electric Loyalty","charge_type":"buy","price":0.425}
{"contract_id":"10_01_147_CHR","target_local_start_timestamp":"2024-10-20T00:00:00.000Z","target_local_end_timestamp":"2024-11-30T00:00:00.000Z","tariff_name":"Business Electric","charge_type":"buy","price":0.2872}
{"contract_id":"10_01_147_CHR","target_local_start_timestamp":"2024-11-30T00:00:00.000Z","target_local_end_timestamp":"2025-01-01T00:00:00.000Z","tariff_name":"Electric Pro","charge_type":"buy","price":0.1815}
{"contract_id":"10_01_147_CHR","target_local_start_timestamp":"2022-12-01T00:00:00.000Z","target_local_end_timestamp":"2023-02-12T00:00:00.000Z","tariff_name":"SState","charge_type":"sell","price":0.0976}
{"contract_id":"10_01_147_CHR","target_local_start_timestamp":"2023-02-12T00:00:00.000Z","target_local_end_timestamp":"2024-05-01T00:00:00.000Z","tariff_name":"SState","charge_type":"sell","price":0.0822}
{"contract_id":"10_01_147_CHR","target_local_start_timestamp":"2024-05-01T00:00:00.000Z","target_local_end_timestamp":"2024-08-10T00:00:00.000Z","tariff_name":"SState","charge_type":"sell","price":0.0684}
{"contract_id":"10_01_147_CHR","target_local_start_timestamp":"2024-08-10T00:00:00.000Z","target_local_end_timestamp":"2024-09-18T00:00:00.000Z","tariff_name":"EctoGrid","charge_type":"sell","price":0.059}
{"contract_id":"10_01_147_CHR","target_local_start_timestamp":"2024-09-18T00:00:00.000Z","target_local_end_timestamp":"2024-10-18T00:00:00.000Z","tariff_name":"OpCom","charge_type":"sell","price":0.0936}
{"contract_id":"10_01_147_CHR","target_local_start_timestamp":"2024-10-18T00:00:00.000Z","target_local_end_timestamp":"2024-11-19T00:00:00.000Z","tariff_name":"EctoGrid","charge_type":"sell","price":0.0665}
{"contract_id":"10_01_147_CHR","target_local_start_timestamp":"2024-11-19T00:00:00.000Z","target_local_end_timestamp":"2024-12-09T00:00:00.000Z","tariff_name":"OpCom","charge_type":"sell","price":0.0988}
{"contract_id":"10_01_147_CHR","target_local_start_timestamp":"2024-12-09T00:00:00.000Z","target_local_end_timestamp":"2025-01-01T00:00:00.000Z","tariff_name":"OpCom","charge_type":"sell","price":0.0423}
{"contract_id":"10_01_147_OR01","target_local_start_timestamp":"2022-12-01T00:00:00.000Z","target_local_end_timestamp":"2023-03-03T00:00:00.000Z","tariff_name":"Digital Electric","charge_type":"buy","price":0.1815}
{"contract_id":"10_01_147_OR01","target_local_start_timestamp":"2023-03-03T00:00:00.000Z","target_local_end_timestamp":"2024-07-01T00:00:00.000Z","tariff_name":"Electric Pro","charge_type":"buy","price":0.151}
{"contract_id":"10_01_147_OR01","target_local_start_timestamp":"2024-07-01T00:00:00.000Z","target_local_end_timestamp":"2024-10-20T00:00:00.000Z","tariff_name":"Eco Electric","charge_type":"buy","price":0.1541}
{"contract_id":"10_01_147_OR01","target_local_start_timestamp":"2024-10-20T00:00:00.000Z","target_local_end_timestamp":"2024-11-30T00:00:00.000Z","tariff_name":"Electric Optim","charge_type":"buy","price":0.2434}
{"contract_id":"10_01_147_OR01","target_local_start_timestamp":"2024-11-30T00:00:00.000Z","target_local_end_timestamp":"2025-01-01T00:00:00.000Z","tariff_name":"Electric Optim","charge_type":"buy","price":0.2225}
{"contract_id":"10_01_147_OR01","target_local_start_timestamp":"2022-12-01T00:00:00.000Z","target_local_end_timestamp":"2023-02-16T00:00:00.000Z","tariff_name":"EctoGrid","charge_type":"sell","price":0.0749}
{"contract_id":"10_01_147_OR01","target_local_start_timestamp":"2023-02-16T00:00:00.000Z","target_local_end_timestamp":"2024-05-19T00:00:00.000Z","tariff_name":"SState","charge_type":"sell","price":0.0916}
{"contract_id":"10_01_147_OR01","target_local_start_timestamp":"2024-05-19T00:00:00.000Z","target_local_end_timestamp":"2024-08-31T00:00:00.000Z","tariff_name":"SState","charge_type":"sell","price":0.1051}
{"contract_id":"10_01_147_OR01","target_local_start_timestamp":"2024-08-31T00:00:00.000Z","target_local_end_timestamp":"2024-10-09T00:00:00.000Z","tariff_name":"EctoGrid","charge_type":"sell","price":0.0518}
{"contract_id":"10_01_147_OR01","target_local_start_timestamp":"2024-10-09T00:00:00.000Z","target_local_end_timestamp":"2024-11-09T00:00:00.000Z","tariff_name":"EctoGrid","charge_type":"sell","price":0.0981}
{"contract_id":"10_01_147_OR01","target_local_start_timestamp":"2024-11-09T00:00:00.000Z","target_local_end_timestamp":"2024-12-11T00:00:00.000Z","tariff_name":"EctoGrid","charge_type":"sell","price":0.0892}
{"contract_id":"10_01_147_OR01","target_local_start_timestamp":"2024-12-11T00:00:00.000Z","target_local_end_timestamp":"2025-01-01T00:00:00.000Z","tariff_name":"SState","charge_type":"sell","price":0.0575}
{"contract_id":"04_02_111_CHR07","target_local_start_timestamp":"2022-12-01T00:00:00.000Z","target_local_end_timestamp":"2023-02-16T00:00:00.000Z","tariff_name":"Business Electric","charge_type":"buy","price":0.1164}
{"contract_id":"04_02_111_CHR07","target_local_start_timestamp":"2023-02-16T00:00:00.000Z","target_local_end_timestamp":"2024-05-19T00:00:00.000Z","tariff_name":"Electric Optim","charge_type":"buy","price":0.1232}
{"contract_id":"04_02_111_CHR07","target_local_start_timestamp":"2024-05-19T00:00:00.000Z","target_local_end_timestamp":"2024-08-31T00:00:00.000Z","tariff_name":"Electric Loyalty","charge_type":"buy","price":0.4171}
{"contract_id":"04_02_111_CHR07","target_local_start_timestamp":"2024-08-31T00:00:00.000Z","target_local_end_timestamp":"2024-10-09T00:00:00.000Z","tariff_name":"Electric Optim","charge_type":"buy","price":0.1762}
{"contract_id":"04_02_111_CHR07","target_local_start_timestamp":"2024-10-09T00:00:00.000Z","target_local_end_timestamp":"2024-11-09T00:00:00.000Z","tariff_name":"Electric Constant","charge_type":"buy","price":0.1039}
{"contract_id":"04_02_111_CHR07","target_local_start_timestamp":"2024-11-09T00:00:00.000Z","target_local_end_timestamp":"2024-12-11T00:00:00.000Z","tariff_name":"Electric Constant","charge_type":"buy","price":0.1607}
{"contract_id":"04_02_111_CHR07","target_local_start_timestamp":"2024-12-11T00:00:00.000Z","target_local_end_timestamp":"2025-01-01T00:00:00.000Z","tariff_name":"Electric Pro","charge_type":"buy","price":0.2181}
{"contract_id":"04_02_111_CHR07","target_local_start_timestamp":"2022-12-01T00:00:00.000Z","target_local_end_timestamp":"2023-06-12T00:00:00.000Z","tariff_name":"EctoGrid","charge_type":"sell","price":0.0746}
{"contract_id":"04_02_111_CHR07","target_local_start_timestamp":"2023-06-12T00:00:00.000Z","target_local_end_timestamp":"2025-01-01T00:00:00.000Z","tariff_name":"OpCom","charge_type":"sell","price":0.102}
{"contract_id":"10_01_147_CHR54","target_local_start_timestamp":"2022-12-01T00:00:00.000Z","target_local_end_timestamp":"2025-01-01T00:00:00.000Z","tariff_name":"Digital Electric","charge_type":"buy","price":0.2641}
{"contract_id":"10_01_147_CHR54","target_local_start_timestamp":"2022-12-01T00:00:00.000Z","target_local_end_timestamp":"2023-03-15T00:00:00.000Z","tariff_name":"SState","charge_type":"sell","price":0.0877}
{"contract_id":"10_01_147_CHR54","target_local_start_timestamp":"2023-03-15T00:00:00.000Z","target_local_end_timestamp":"2024-08-25T00:00:00.000Z","tariff_name":"OpCom","charge_type":"sell","price":0.0818}
{"contract_id":"10_01_147_CHR54","target_local_start_timestamp":"2024-08-25T00:00:00.000Z","target_local_end_timestamp":"2025-01-01T00:00:00.000Z","tariff_name":"EctoGrid","charge_type":"sell","price":0.0562}
{"contract_id":"04_02_111_CHS01","target_local_start_timestamp":"2022-12-01T00:00:00.000Z","target_local_end_timestamp":"2023-03-03T00:00:00.000Z","tariff_name":"Eco Electric","charge_type":"buy","price":0.1519}
{"contract_id":"04_02_111_CHS01","target_local_start_timestamp":"2023-03-03T00:00:00.000Z","target_local_end_timestamp":"2024-07-01T00:00:00.000Z","tariff_name":"Digital Electric","charge_type":"buy","price":0.2181}
{"contract_id":"04_02_111_CHS01","target_local_start_timestamp":"2024-07-01T00:00:00.000Z","target_local_end_timestamp":"2024-10-20T00:00:00.000Z","tariff_name":"Electric Pro","charge_type":"buy","price":0.2034}
{"contract_id":"04_02_111_CHS01","target_local_start_timestamp":"2024-10-20T00:00:00.000Z","target_local_end_timestamp":"2024-11-30T00:00:00.000Z","tariff_name":"Electric Optim","charge_type":"buy","price":0.1394}
{"contract_id":"04_02_111_CHS01","target_local_start_timestamp":"2024-11-30T00:00:00.000Z","target_local_end_timestamp":"2025-01-01T00:00:00.000Z","tariff_name":"Electric Loyalty","charge_type":"buy","price":0.4067}
{"contract_id":"04_02_111_CHS01","target_local_start_timestamp":"2022-12-01T00:00:00.000Z","target_local_end_timestamp":"2025-01-01T00:00:00.000Z","tariff_name":"SState","charge_type":"sell","price":0.0736}
{"contract_id":"04_02_111_CHR11","target_local_start_timestamp":"2022-12-01T00:00:00.000Z","target_local_end_timestamp":"2023-02-16T00:00:00.000Z","tariff_name":"Electric Loyalty","charge_type":"buy","price":0.4347}
{"contract_id":"04_02_111_CHR11","target_local_start_timestamp":"2023-02-16T00:00:00.000Z","target_local_end_timestamp":"2024-06-04T00:00:00.000Z","tariff_name":"Digital Electric","charge_type":"buy","price":0.1723}
{"contract_id":"04_02_111_CHR11","target_local_start_timestamp":"2024-06-04T00:00:00.000Z","target_local_end_timestamp":"2024-09-19T00:00:00.000Z","tariff_name":"Business Electric","charge_type":"buy","price":0.4005}
{"contract_id":"04_02_111_CHR11","target_local_start_timestamp":"2024-09-19T00:00:00.000Z","target_local_end_timestamp":"2024-10-29T00:00:00.000Z","tariff_name":"Eco Electric","charge_type":"buy","price":0.1862}
{"contract_id":"04_02_111_CHR11","target_local_start_timestamp":"2024-10-29T00:00:00.000Z","target_local_end_timestamp":"2024-11-29T00:00:00.000Z","tariff_name":"Digital Electric","charge_type":"buy","price":0.1591}
{"contract_id":"04_02_111_CHR11","target_local_start_timestamp":"2024-11-29T00:00:00.000Z","target_local_end_timestamp":"2025-01-01T00:00:00.000Z","tariff_name":"Electric Constant","charge_type":"buy","price":0.2058}
{"contract_id":"04_02_111_CHR11","target_local_start_timestamp":"2022-12-01T00:00:00.000Z","target_local_end_timestamp":"2023-06-12T00:00:00.000Z","tariff_name":"SState","charge_type":"sell","price":0.0761}
{"contract_id":"04_02_111_CHR11","target_local_start_timestamp":"2023-06-12T00:00:00.000Z","target_local_end_timestamp":"2025-01-01T00:00:00.000Z","tariff_name":"SState","charge_type":"sell","price":0.0557}
{"contract_id":"10_01_147_CHR14","target_local_start_timestamp":"2022-12-01T00:00:00.000Z","target_local_end_timestamp":"2023-06-12T00:00:00.000Z","tariff_name":"Electric Optim","charge_type":"buy","price":0.2648}
{"contract_id":"10_01_147_CHR14","target_local_start_timestamp":"2023-06-12T00:00:00.000Z","target_local_end_timestamp":"2025-01-01T00:00:00.000Z","tariff_name":"Electric Constant","charge_type":"buy","price":0.1774}
{"contract_id":"10_01_147_CHR14","target_local_start_timestamp":"2022-12-01T00:00:00.000Z","target_local_end_timestamp":"2023-03-15T00:00:00.000Z","tariff_name":"EctoGrid","charge_type":"sell","price":0.0884}
{"contract_id":"10_01_147_CHR14","target_local_start_timestamp":"2023-03-15T00:00:00.000Z","target_local_end_timestamp":"2024-08-25T00:00:00.000Z","tariff_name":"SState","charge_type":"sell","price":0.1047}
{"contract_id":"10_01_147_CHR14","target_local_start_timestamp":"2024-08-25T00:00:00.000Z","target_local_end_timestamp":"2025-01-01T00:00:00.000Z","tariff_name":"OpCom","charge_type":"sell","price":0.0643}
{"contract_id":"04_02_111_CHR30","target_local_start_timestamp":"2022-12-01T00:00:00.000Z","target_local_end_timestamp":"2023-03-03T00:00:00.000Z","tariff_name":"Business Electric","charge_type":"buy","price":0.1858}
{"contract_id":"04_02_111_CHR30","target_local_start_timestamp":"2023-03-03T00:00:00.000Z","target_local_end_timestamp":"2024-07-29T00:00:00.000Z","tariff_name":"Business Electric","charge_type":"buy","price":0.2124}
{"contract_id":"04_02_111_CHR30","target_local_start_timestamp":"2024-07-29T00:00:00.000Z","target_local_end_timestamp":"2024-11-18T00:00:00.000Z","tariff_name":"Digital Electric","charge_type":"buy","price":0.1782}
{"contract_id":"04_02_111_CHR30","target_local_start_timestamp":"2024-11-18T00:00:00.000Z","target_local_end_timestamp":"2025-01-01T00:00:00.000Z","tariff_name":"Eco Electric","charge_type":"buy","price":0.1}
{"contract_id":"04_02_111_CHR30","target_local_start_timestamp":"2022-12-01T00:00:00.000Z","target_local_end_timestamp":"2023-02-16T00:00:00.000Z","tariff_name":"OpCom","charge_type":"sell","price":0.0776}
{"contract_id":"04_02_111_CHR30","target_local_start_timestamp":"2023-02-16T00:00:00.000Z","target_local_end_timestamp":"2024-06-04T00:00:00.000Z","tariff_name":"EctoGrid","charge_type":"sell","price":0.0451}
{"contract_id":"04_02_111_CHR30","target_local_start_timestamp":"2024-06-04T00:00:00.000Z","target_local_end_timestamp":"2024-09-19T00:00:00.000Z","tariff_name":"EctoGrid","charge_type":"sell","price":0.1054}
{"contract_id":"04_02_111_CHR30","target_local_start_timestamp":"2024-09-19T00:00:00.000Z","target_local_end_timestamp":"2024-10-29T00:00:00.000Z","tariff_name":"OpCom","charge_type":"sell","price":0.0852}
{"contract_id":"04_02_111_CHR30","target_local_start_timestamp":"2024-10-29T00:00:00.000Z","target_local_end_timestamp":"2024-11-29T00:00:00.000Z","tariff_name":"SState","charge_type":"sell","price":0.1071}
{"contract_id":"04_02_111_CHR30","target_local_start_timestamp":"2024-11-29T00:00:00.000Z","target_local_end_timestamp":"2025-01-01T00:00:00.000Z","tariff_name":"SState","charge_type":"sell","price":0.1043}
